mrseql/__init__.py
mrseql/mrseql.cpython-312-x86_64-linux-gnu.so
mrseql.libs/libfftw3-6b983104.so.3.5.5
mrseql-0.0.4.dist-info/RECORD
mrseql-0.0.4.dist-info/top_level.txt
mrseql-0.0.4.dist-info/LICENSE
mrseql-0.0.4.dist-info/WHEEL
mrseql-0.0.4.dist-info/METADATA
