Metadata-Version: 2.1
Name: mrseql
Version: 0.0.4
Summary: MrSEQL
Author: Thach Le Nguyen
Author-email: thalng@protonmail.com
Requires-Python: >=3.7
License-File: LICENSE
